pydoautomator/__init__.py
pydoautomator/adapters.py
pydoautomator/automator.py
pydoautomator/droplet.py
pydoautomator/errors.py
pydoautomator-0.8.3.dist-info/LICENSE
pydoautomator-0.8.3.dist-info/WHEEL
pydoautomator-0.8.3.dist-info/METADATA
pydoautomator-0.8.3.dist-info/RECORD
