Metadata-Version: 2.1
Name: pydoautomator
Version: 0.8.3
Summary: The Python lib for digital ocean automation
Home-page: https://github.com/christian-hawk/pydoautomator
License: Apache-2.0
Author: Christian Eland
Author-email: eland.christian@gmail.com
Requires-Python: >=3.6.1,<4.0.0
Classifier: Development Status :: 4 - Beta
Classifier: License :: OSI Approved :: Apache Software License
Classifier: Operating System :: OS Independent
Classifier: Programming Language :: Python :: 3
Classifier: Programming Language :: Python :: 3.7
Classifier: Programming Language :: Python :: 3.8
Classifier: Programming Language :: Python :: 3.9
Requires-Dist: importlib-metadata (>=2.0.0,<3.0.0)
Requires-Dist: pydantic (>=1.6.1,<2.0.0)
Requires-Dist: requests (>=2.24.0,<3.0.0)
Project-URL: Documentation, https://pydoautomator.readthedocs.io
Project-URL: Repository, https://github.com/christian-hawk/pydoautomator
